streamlit_toggle_diy/__init__.py
streamlit_toggle_diy/frontend/build/asset-manifest.json
streamlit_toggle_diy/frontend/build/bootstrap.min.css
streamlit_toggle_diy/frontend/build/index.html
streamlit_toggle_diy/frontend/build/precache-manifest.208239bd31634c912148876425127f2c.js
streamlit_toggle_diy/frontend/build/precache-manifest.668eb5ddc0ea6880d50beeba97fd93a9.js
streamlit_toggle_diy/frontend/build/precache-manifest.669f85f994ea2c0d193915faa9d91f97.js
streamlit_toggle_diy/frontend/build/precache-manifest.b7df6085566f07f8f27b94ee8ed2d302.js
streamlit_toggle_diy/frontend/build/service-worker.js
streamlit_toggle_diy/frontend/build/static/js/2.82cd69ef.chunk.js
streamlit_toggle_diy/frontend/build/static/js/2.82cd69ef.chunk.js.LICENSE.txt
streamlit_toggle_diy/frontend/build/static/js/2.82cd69ef.chunk.js.map
streamlit_toggle_diy/frontend/build/static/js/2.8590d27d.chunk.js
streamlit_toggle_diy/frontend/build/static/js/2.8590d27d.chunk.js.LICENSE.txt
streamlit_toggle_diy/frontend/build/static/js/2.8590d27d.chunk.js.map
streamlit_toggle_diy/frontend/build/static/js/2.9720bf9e.chunk.js
streamlit_toggle_diy/frontend/build/static/js/2.9720bf9e.chunk.js.LICENSE.txt
streamlit_toggle_diy/frontend/build/static/js/2.9720bf9e.chunk.js.map
streamlit_toggle_diy/frontend/build/static/js/main.72a874a0.chunk.js
streamlit_toggle_diy/frontend/build/static/js/main.72a874a0.chunk.js.map
streamlit_toggle_diy/frontend/build/static/js/main.93eb9d37.chunk.js
streamlit_toggle_diy/frontend/build/static/js/main.93eb9d37.chunk.js.map
streamlit_toggle_diy/frontend/build/static/js/main.9f3c3eed.chunk.js
streamlit_toggle_diy/frontend/build/static/js/main.9f3c3eed.chunk.js.map
streamlit_toggle_diy/frontend/build/static/js/main.d5e2b6f4.chunk.js
streamlit_toggle_diy/frontend/build/static/js/main.d5e2b6f4.chunk.js.map
streamlit_toggle_diy/frontend/build/static/js/runtime-main.cc20bba3.js
streamlit_toggle_diy/frontend/build/static/js/runtime-main.cc20bba3.js.map
streamlit_toggle_diy-1.1.7.dist-info/LICENSE
streamlit_toggle_diy-1.1.7.dist-info/METADATA
streamlit_toggle_diy-1.1.7.dist-info/WHEEL
streamlit_toggle_diy-1.1.7.dist-info/top_level.txt
streamlit_toggle_diy-1.1.7.dist-info/RECORD
